bughotspots/__init__.py
bughotspots-0.5.dist-info/LICENSE
bughotspots-0.5.dist-info/METADATA
bughotspots-0.5.dist-info/WHEEL
bughotspots-0.5.dist-info/entry_points.txt
bughotspots-0.5.dist-info/top_level.txt
bughotspots-0.5.dist-info/RECORD
