Metadata-Version: 2.1
Name: bughotspots
Version: 0.5
Summary: A Python based implementation of the bug prediction algorithm proposed by Google
Home-page: https://github.com/pntgoswami18/python-bugspots
Author: Punit Goswami
License: BSD
Keywords: bughotspot bug spots bug prediction
Platform: UNKNOWN
Classifier: Development Status :: 4 - Beta
Classifier: Intended Audience :: Developers
Classifier: Operating System :: Unix 
License-File: LICENSE
Requires-Dist: vcstools-latest
